trendverify/_test.py
trendverify/find_files.py
trendverify/metar.py
trendverify/project_utils.py
trendverify/script_metar_2021.py
trendverify/trend.py
trendverify/verificationcodes.py
TrendVerify-0.0.3.post1.dist-info/METADATA
TrendVerify-0.0.3.post1.dist-info/WHEEL
TrendVerify-0.0.3.post1.dist-info/entry_points.txt
TrendVerify-0.0.3.post1.dist-info/top_level.txt
TrendVerify-0.0.3.post1.dist-info/RECORD
