Metadata-Version: 2.1
Name: TrendVerify
Version: 0.0.3.post1
Requires-Dist: tzdata (>=2022.7)
Requires-Dist: regex (>=2022.10.31)
Requires-Dist: importlib-metadata ; python_version >= "3.10"
